LICENSE
MANIFEST.in
README.rst
setup.cfg
setup.py
tox.ini
metaextract/__init__.py
metaextract/cmds.py
metaextract/metaextract.py
metaextract/setup.py
metaextract/utils.py
metaextract.egg-info/PKG-INFO
metaextract.egg-info/SOURCES.txt
metaextract.egg-info/dependency_links.txt
metaextract.egg-info/entry_points.txt
metaextract.egg-info/top_level.txt