Metadata-Version: 1.1
Name: metaextract
Version: 1.0.3
Summary: get metadata for python modules
Home-page: http://github.com/toabctl/metaextract
Author: Thomas Bechtold
Author-email: thomasbechtold@jpberlin.de
License: Apache-2.0
Platform: UNKNOWN
Classifier: Development Status :: 5 - Production/Stable
Classifier: Environment :: Console
Classifier: License :: OSI Approved :: Apache Software License
Classifier: Programming Language :: Python
